SyDataSets/__init__.py
SyDataSets/dataset.py
SyDataSets/requirements.txt
SyDataSets/utils/__init__.py
SyDataSets/utils/util.py
SyDataSets-0.0.4.dist-info/LICENSE
SyDataSets-0.0.4.dist-info/METADATA
SyDataSets-0.0.4.dist-info/WHEEL
SyDataSets-0.0.4.dist-info/top_level.txt
SyDataSets-0.0.4.dist-info/RECORD
