Metadata-Version: 2.1
Name: SyDataSets
Version: 0.0.4
Summary: Provided to meteplus for data processing
Author: zhuchao
Author-email: zhuchao@meteplus.com
Requires-Python: >=3.6
License-File: LICENSE
Requires-Dist: requests
Requires-Dist: tqdm
